pycbg/MPMxDEM.py
pycbg/__init__.py
pycbg/_version.py
pycbg/command_line_script.py
pycbg/postprocessing.py
pycbg/preprocessing.py
pycbg-2.0.1.dist-info/licenses/LICENSE.txt
tests/gener_expected_vals.py
tests/test_preprocessing.py
pycbg-2.0.1.dist-info/METADATA
pycbg-2.0.1.dist-info/WHEEL
pycbg-2.0.1.dist-info/entry_points.txt
pycbg-2.0.1.dist-info/top_level.txt
pycbg-2.0.1.dist-info/zip-safe
pycbg-2.0.1.dist-info/RECORD
