Metadata-Version: 2.4
Name: pycbg
Version: 2.0.1
Summary: Python scripts able to generate easily CB-Geo MPM input files
Author-email: Sacha Duverger <sacha.duverger@univ-amu.fr>, Jérôme Duriez <jerome.duriez@inrae.fr>
License: MIT
Project-URL: Homepage, https://forge.inrae.fr/mpm-at-recover/pycbg.git
Project-URL: Repository, https://forge.inrae.fr/mpm-at-recover/pycbg.git
Project-URL: Documentation, https://pycbg.readthedocs.io/en/latest/
License-File: LICENSE.txt
Requires-Dist: numpy>=1.20.3
Requires-Dist: gmsh
Requires-Dist: pandas
Requires-Dist: matplotlib
Requires-Dist: pyreadline
Requires-Dist: sphinx==5.1.1
Requires-Dist: sphinx_rtd_theme==0.5.2
Provides-Extra: full
Requires-Dist: ipython; extra == "full"
Dynamic: license-file
